CHANGELOG.md
tri_again/__init__.py
tri_again/_collada.py
tri_again/_color.py
tri_again/_scene.py
tri_again/_scene_internal.py
tri_again-1.1.2.dist-info/LICENSE
tri_again-1.1.2.dist-info/WHEEL
tri_again-1.1.2.dist-info/METADATA
tri_again-1.1.2.dist-info/RECORD
